fredio/__init__.py
fredio/client.py
fredio/const.py
fredio/events.py
fredio/locks.py
fredio/utils.py
fredio-0.2.0.dist-info/LICENSE
fredio-0.2.0.dist-info/METADATA
fredio-0.2.0.dist-info/WHEEL
fredio-0.2.0.dist-info/top_level.txt
fredio-0.2.0.dist-info/RECORD
