Metadata-Version: 2.1
Name: fredio
Version: 0.2.0
Summary: Asynchronous python client for the FRED® API
Home-page: https://github.com/bgrams/fredio
Author: Brandon Grams
License: MIT
Platform: UNKNOWN
Classifier: Development Status :: 3 - Alpha
Classifier: Framework :: AsyncIO
Classifier: Intended Audience :: Developers
Classifier: License :: OSI Approved :: MIT License
Classifier: Natural Language :: English
Classifier: Programming Language :: Python :: 3
Classifier: Programming Language :: Python :: 3.6
Classifier: Programming Language :: Python :: 3.7
Classifier: Programming Language :: Python :: 3.8
Classifier: Programming Language :: Python :: 3.9
Requires-Python: >=3.6
License-File: LICENSE
Requires-Dist: aiohttp (<4.0,>=3.0)
Requires-Dist: jsonpath-rw
Requires-Dist: pandas
Requires-Dist: yarl (<2.0,>=1.0)
Requires-Dist: typing-extensions
